jrm09/Globals.py
jrm09/Model.py
jrm09/ModelCart.py
jrm09/Test.py
jrm09/_CoeffGrids.py
jrm09/_Legendre.py
jrm09/_ReadCoeffs.py
jrm09/_Schmidt.py
jrm09/_SphHarm.py
jrm09/__init__.py
jrm09/__data/coeffs.dat
jrm09-1.0.0.dist-info/LICENSE
jrm09-1.0.0.dist-info/METADATA
jrm09-1.0.0.dist-info/WHEEL
jrm09-1.0.0.dist-info/top_level.txt
jrm09-1.0.0.dist-info/RECORD
