Metadata-Version: 2.1
Name: jrm09
Version: 1.0.0
Summary: Python implementation of the JRM09 model
Home-page: https://github.com/mattkjames7/jrm09
Author: Matthew Knight James
Author-email: mattkjames7@gmail.com
License: UNKNOWN
Platform: UNKNOWN
Classifier: Programming Language :: Python :: 3
Classifier: License :: OSI Approved :: MIT License
Classifier: Operating System :: POSIX
Requires-Dist: numpy
Requires-Dist: PyFileIO
